primitize/__init__.py
primitize/core.py
primitize/py.typed
primitize-2021.6.24.dist-info/LICENSE
primitize-2021.6.24.dist-info/METADATA
primitize-2021.6.24.dist-info/WHEEL
primitize-2021.6.24.dist-info/top_level.txt
primitize-2021.6.24.dist-info/RECORD
