Metadata-Version: 2.1
Name: primitize
Version: 2021.6.24
Summary: Primitize is a library that facilitates converting dataclass instances into primitive objects.
Home-page: https://github.com/nanassito/primitize
Author: Dorian Jaminais
Author-email: primitize@jaminais.fr
License: UNKNOWN
Platform: UNKNOWN
Classifier: Programming Language :: Python :: 3
Classifier: License :: Public Domain
Classifier: Operating System :: OS Independent
Requires-Python: >=3.6
License-File: LICENSE
Requires-Dist: typing-extensions
